fsmate/__init__.py
fsmate/_state.py
fsmate/py.typed
fsmate-0.2.0.dist-info/METADATA
fsmate-0.2.0.dist-info/WHEEL
fsmate-0.2.0.dist-info/RECORD
